{"width":1024,"height":1024,"name":"Gen_Anim_44","imagePath":"Gen_Anim_44_tex.png","SubTexture":[{"width":28,"y":986,"height":35,"name":"shoubijia2hhh","x":102},{"frameHeight":21,"y":138,"frameWidth":28,"frameX":-1,"width":26,"frameY":-1,"height":20,"name":"houshou2","x":911},{"frameHeight":53,"y":902,"frameWidth":37,"frameX":-1,"width":36,"frameY":-1,"height":51,"name":"wuqibing","x":987},{"width":62,"y":918,"height":55,"name":"houshou1","x":1},{"width":127,"y":285,"height":120,"name":"shoubijia2qian","x":708},{"width":59,"y":217,"height":82,"name":"jinajia2mao","x":943},{"width":88,"y":828,"height":72,"name":"xionghoujiahou","x":930},{"width":100,"y":913,"height":92,"name":"neiyi","x":885},{"width":58,"y":447,"height":64,"name":"jiayaohou221","x":930},{"width":187,"y":162,"height":119,"name":"neijia","x":465},{"width":461,"y":516,"height":400,"name":"kuzi","x":1},{"width":39,"y":918,"height":79,"name":"yjh1","x":154},{"width":103,"y":913,"height":96,"name":"yaojiaqiansda","x":682},{"width":99,"y":975,"height":34,"name":"qunqianshang2","x":1},{"width":332,"y":516,"height":154,"name":"qjhx21","x":464},{"width":82,"y":730,"height":96,"name":"qunjiahoushang1qu","x":930},{"width":216,"y":1,"height":159,"name":"qunqianxia1","x":465},{"width":186,"y":172,"height":111,"name":"qunjiaqianshang1","x":654},{"width":63,"y":138,"height":77,"name":"yaoguitou","x":943},{"width":199,"y":1,"height":169,"name":"xiongjiaqian","x":683},{"width":50,"y":918,"height":66,"name":"jian22","x":102},{"width":115,"y":407,"height":88,"name":"shoubi1hou","x":708},{"width":103,"y":447,"height":45,"name":"jianajia1maohou","x":825},{"width":99,"y":172,"height":174,"name":"maoweibo3","x":842},{"width":228,"y":730,"height":181,"name":"maoweibo2","x":700},{"width":117,"y":285,"height":141,"name":"maoweibo","x":589},{"width":234,"y":672,"height":180,"name":"jianjiamaoqian","x":464},{"width":151,"y":348,"height":97,"name":"jianjia1xia","x":837},{"width":205,"y":516,"height":212,"name":"jianjia1shang","x":798},{"width":99,"y":442,"height":57,"name":"das","x":465},{"width":216,"y":854,"height":166,"name":"shoubijia","x":464},{"width":96,"y":913,"height":96,"name":"qianshou","x":787},{"width":44,"y":966,"height":57,"name":"shoubiqianj","x":195},{"width":90,"y":672,"height":38,"name":"tou2","x":700},{"width":122,"y":283,"height":157,"name":"lian","x":465},{"width":124,"y":1,"height":135,"name":"tou1","x":884},{"width":102,"y":428,"height":78,"name":"huzi1","x":589},{"width":59,"y":918,"height":46,"name":"qiansuifa","x":195},{"width":462,"y":1,"height":513,"name":"wuqi","x":1},{"width":18,"y":918,"height":27,"name":"5","x":65},{"width":18,"y":481,"height":32,"name":"4","x":566},{"width":19,"y":442,"height":37,"name":"3","x":566},{"width":17,"y":955,"height":28,"name":"2","x":987},{"width":25,"y":138,"height":29,"name":"1","x":884},{"width":36,"y":999,"height":22,"name":"0","x":132},{"frameHeight":11,"y":902,"frameWidth":47,"frameX":-1,"width":45,"frameY":-1,"height":9,"name":"biyan","x":930}]}