{"SubTexture":[{"frameHeight":210,"y":135,"frameWidth":210,"frameX":-33,"width":122,"frameY":-34,"height":131,"name":"wjzj_s_0003","x":126},{"frameHeight":210,"y":2,"frameWidth":210,"frameX":-33,"width":122,"frameY":-34,"height":131,"name":"wjzj_s_0006","x":126},{"frameHeight":210,"y":268,"frameWidth":210,"frameX":-33,"width":122,"frameY":-34,"height":131,"name":"wjzj_s_0002","x":2},{"frameHeight":210,"y":268,"frameWidth":210,"frameX":-33,"width":121,"frameY":-34,"height":131,"name":"wjzj_s_0001","x":126},{"frameHeight":210,"y":135,"frameWidth":210,"frameX":-33,"width":122,"frameY":-34,"height":131,"name":"wjzj_s_0004","x":2},{"frameHeight":210,"y":2,"frameWidth":210,"frameX":-33,"width":122,"frameY":-34,"height":131,"name":"wjzj_s_0005","x":2}],"width":256,"imagePath":"HangGen46_tex.png","height":512,"name":"HangGen46"}